isek/__init__.py
isek/cli.py
isek/exceptions.py
isek/adapter/__init__.py
isek/adapter/open_ai_sdk_adapter.py
isek/adapter/pydantic_ai_adapter.py
isek/node/__init__.py
isek/node/node_v3_a2a.py
isek/protocol/__init__.py
isek/protocol/a2a_protocol_v2.py
isek/protocol/p2p/p2p_server.js
isek/protocol/p2p/package.json
isek/protocol/p2p/pnpm-lock.yaml
isek/protocol/p2p/relay.js
isek/utils/__init__.py
isek/utils/common.py
isek/utils/log.py
isek/utils/print_utils.py
isek/utils/tools.py
isek/web3/isek_identiey.py
isek/web3/wallet_manager.py
isek/web3/abi/IdentityRegistry.json
isek-0.3.3.dist-info/METADATA
isek-0.3.3.dist-info/WHEEL
isek-0.3.3.dist-info/entry_points.txt
isek-0.3.3.dist-info/licenses/LICENSE
isek-0.3.3.dist-info/RECORD
