Metadata-Version: 2.4
Name: isek
Version: 0.3.3
Summary: ISEK Distributed Multi-Agent Framework
Author-email: ISEK Team <sparks@isek.xyz>
License: MIT
License-File: LICENSE
Keywords: AI,LLM,distributed,multi-agent
Requires-Python: >=3.10
Requires-Dist: a2a-sdk
Requires-Dist: click>=8.0.0
Requires-Dist: eth-account>=0.9.0
Requires-Dist: httpx>=0.25.0
Requires-Dist: pre-commit
Requires-Dist: pydantic-ai
Requires-Dist: python-dotenv
Requires-Dist: rich
Requires-Dist: uvicorn
Requires-Dist: web3>=6.0.0
